dbgear_doc/__init__.py
dbgear_doc/command.py
dbgear_doc/diagram.py
dbgear_doc/er_diagram.py
dbgear_doc/generator.py
dbgear_doc-0.5.0.dist-info/METADATA
dbgear_doc-0.5.0.dist-info/WHEEL
dbgear_doc-0.5.0.dist-info/entry_points.txt
dbgear_doc-0.5.0.dist-info/licenses/LICENSE
dbgear_doc-0.5.0.dist-info/RECORD
