Metadata-Version: 2.4
Name: dbgear-doc
Version: 0.5.0
Summary: Documentation generator plugin for DBGear
License-Expression: MIT
License-File: LICENSE
Author: tamuto
Author-email: mutomob@gmail.com
Requires-Python: >=3.12,<4.0
Classifier: Programming Language :: Python :: 3
Classifier: Programming Language :: Python :: 3.12
Classifier: Programming Language :: Python :: 3.13
Classifier: Programming Language :: Python :: 3.14
Requires-Dist: dbgear (>=0.40.0)
Requires-Dist: in4viz (>=0.3.0)
